chiefpaay/__init__.py
chiefpaay/client.py
chiefpaay/core/__init__.py
chiefpaay/core/api_error.py
chiefpaay/core/client_wrapper.py
chiefpaay/core/datetime_utils.py
chiefpaay/core/file.py
chiefpaay/core/force_multipart.py
chiefpaay/core/http_client.py
chiefpaay/core/http_response.py
chiefpaay/core/http_sse/__init__.py
chiefpaay/core/http_sse/_api.py
chiefpaay/core/http_sse/_decoders.py
chiefpaay/core/http_sse/_exceptions.py
chiefpaay/core/http_sse/_models.py
chiefpaay/core/jsonable_encoder.py
chiefpaay/core/pydantic_utilities.py
chiefpaay/core/query_encoder.py
chiefpaay/core/remove_none_from_dict.py
chiefpaay/core/request_options.py
chiefpaay/core/serialization.py
chiefpaay/environment.py
chiefpaay/errors/__init__.py
chiefpaay/errors/bad_request_error.py
chiefpaay/errors/unauthorized_error.py
chiefpaay/py.typed
chiefpaay/raw_client.py
chiefpaay/types/__init__.py
chiefpaay/types/chain_token_invoice.py
chiefpaay/types/chain_token_static.py
chiefpaay/types/error_response.py
chiefpaay/types/error_response_message.py
chiefpaay/types/error_status_code.py
chiefpaay/types/fiat_details.py
chiefpaay/types/get_history_request.py
chiefpaay/types/invoice.py
chiefpaay/types/invoice_status.py
chiefpaay/types/invoices.py
chiefpaay/types/last_transaction.py
chiefpaay/types/rate.py
chiefpaay/types/static_wallet.py
chiefpaay/types/static_wallet_notification.py
chiefpaay/types/success_response_invoice.py
chiefpaay/types/success_response_invoices.py
chiefpaay/types/success_response_rate_array.py
chiefpaay/types/success_response_static_wallet.py
chiefpaay/types/success_response_transactions.py
chiefpaay/types/transaction.py
chiefpaay/types/transactions.py
chiefpaay/types/uuid_.py
chiefpaay/version.py
test_chiefpay_fern-0.0.14.dist-info/METADATA
test_chiefpay_fern-0.0.14.dist-info/WHEEL
test_chiefpay_fern-0.0.14.dist-info/RECORD
